pydatagrid/__init__.py
pydatagrid/datagrid.py
pydatagrid/flask_integration.py
pydatagrid/static/css/datagrid.css
pydatagrid/static/js/datagrid.js
pydatagrid/templates/datagrid.html
pydatagrid-1.0.0.dist-info/LICENSE
pydatagrid-1.0.0.dist-info/METADATA
pydatagrid-1.0.0.dist-info/WHEEL
pydatagrid-1.0.0.dist-info/top_level.txt
pydatagrid-1.0.0.dist-info/RECORD
