Metadata-Version: 2.1
Name: pydatagrid
Version: 1.0.0
Summary: A powerful data grid library with sorting, filtering, pagination, and export features
Home-page: https://github.com/yourusername/pydatagrid
Author: PyDataGrid Team
Author-email: info@pydatagrid.com
Classifier: Programming Language :: Python :: 3
Classifier: License :: OSI Approved :: MIT License
Classifier: Operating System :: OS Independent
Classifier: Development Status :: 4 - Beta
Classifier: Intended Audience :: Developers
Classifier: Topic :: Software Development :: Libraries :: Python Modules
Requires-Python: >=3.7
License-File: LICENSE
Requires-Dist: Flask >=2.0.0
Requires-Dist: flask-cors >=3.0.0
